cursed_trim/__init__.py
cursed_trim-0.1.0.dist-info/WHEEL
cursed_trim-0.1.0.dist-info/METADATA
cursed_trim-0.1.0.dist-info/RECORD
